pyproject_pre_commit/__init__.py
pyproject_pre_commit/__version__.py
pyproject_pre_commit/py.typed
pyproject_pre_commit/pyproject_pre_commit.py
pyproject_pre_commit-0.5.2.dist-info/METADATA
pyproject_pre_commit-0.5.2.dist-info/WHEEL
pyproject_pre_commit-0.5.2.dist-info/entry_points.txt
pyproject_pre_commit-0.5.2.dist-info/licenses/LICENSE
pyproject_pre_commit-0.5.2.dist-info/RECORD
