Metadata-Version: 2.4
Name: pyproject-pre-commit
Version: 0.5.2
Summary: pre-commit hooks for python projects using pyproject.toml.
Project-URL: Repository, https://github.com/rcmdnk/pyproject-pre-commit
Project-URL: Documentation, https://github.com/rcmdnk/pyproject-pre-commit
Project-URL: Homepage, https://github.com/rcmdnk/pyproject-pre-commit
Project-URL: Issue, https://github.com/rcmdnk/pyproject-pre-commit/issues
Author-email: rcmdnk <rcmdnk@gmail.com>
License-Expression: Apache-2.0
License-File: LICENSE
Keywords: pre-commit,pyproject.toml,uv
Classifier: Development Status :: 3 - Alpha
Classifier: Environment :: Console
Classifier: Intended Audience :: Developers
Classifier: Operating System :: OS Independent
Classifier: Topic :: Software Development
Classifier: Topic :: Software Development :: Libraries :: Python Modules
Classifier: Topic :: Utilities
Requires-Python: >=3.9.0
Requires-Dist: mdformat-beautysh>=0.1.1
Requires-Dist: mdformat-config>=0.2.1
Requires-Dist: mdformat-footnote>=0.1.1
Requires-Dist: mdformat-frontmatter>=2.0.1
Requires-Dist: mdformat-gfm>=0.3.5
Requires-Dist: mdformat-gofmt>=0.0.2
Requires-Dist: mdformat-pyproject>=0.0.1
Requires-Dist: mdformat-ruff>=0.1.3
Requires-Dist: mdformat-rustfmt>=0.0.3
Requires-Dist: mdformat-tables>=1.0.0
Requires-Dist: mdformat-toc>=0.3.0
Requires-Dist: mdformat-web>=0.2.0
Requires-Dist: mdformat>=0.7.17
Requires-Dist: mypy>=1.5.1
Requires-Dist: numpydoc>=1.8.0
Requires-Dist: pre-commit>=4.0.0
Requires-Dist: shellcheck-py>=0.9.0.5
Requires-Dist: validate-pyproject[all]>=0.22
Provides-Extra: black
Requires-Dist: autoflake>=2.2.1; extra == 'black'
Requires-Dist: autopep8>=2.0.4; extra == 'black'
Requires-Dist: bandit[toml]>=1.7.5; extra == 'black'
Requires-Dist: black>=24.3.0; extra == 'black'
Requires-Dist: blacken-docs>=1.16.0; extra == 'black'
Requires-Dist: flake8-annotations-complexity>=0.0.8; extra == 'black'
Requires-Dist: flake8-bugbear>=24.0.0; extra == 'black'
Requires-Dist: flake8-builtins>=2.1.0; extra == 'black'
Requires-Dist: flake8-comprehensions>=3.14.0; extra == 'black'
Requires-Dist: flake8-debugger>=4.1.2; extra == 'black'
Requires-Dist: flake8-docstrings>=1.7.0; extra == 'black'
Requires-Dist: flake8-executable>=2.1.3; extra == 'black'
Requires-Dist: flake8-pep3101>=2.0.0; extra == 'black'
Requires-Dist: flake8-print>=5.0.0; extra == 'black'
Requires-Dist: flake8-pyproject>=1.2.3; extra == 'black'
Requires-Dist: flake8-rst-docstrings>=0.3.0; extra == 'black'
Requires-Dist: flake8-string-format>=0.3.0; extra == 'black'
Requires-Dist: isort>=5.12.0; extra == 'black'
Requires-Dist: pep8-naming>=0.14.0; extra == 'black'
Requires-Dist: pycodestyle>=2.11.0; extra == 'black'
Provides-Extra: ruff
Requires-Dist: ruff>=0.7.2; extra == 'ruff'
Provides-Extra: ty
Requires-Dist: ty>=0.0.7; extra == 'ty'
